libgensio_afskmdm.so
libgensio.so
_gensio.so
libgensio_script.so
libgensio_telnet.so
libgensio_mux.so
libgensio_serialdev.so
libgensiomdns.so.4
libgensio_stdio.so
libgensio_python_swig.so.4.0.0
libgensio_file.so
libgensio_pty.so
libgensioosh.so.4.0.0
libgensio_net.so
libgensio_sound.so
libgensio_echo.so
libgensio_keepopen.so
libgensio_ax25.so
gensio.py
libgensio_udp.so
libgensio_python_swig.so
libgensioosh.so.4
libgensio_trace.so
libgensio.so.4.0.0
libgensioosh.so
libgensio.so.4
libgensio_conacc.so
libgensiomdns.so
libgensio_xlt.so
libgensio_relpkt.so
libgensio_ratelimit.so
libgensio_dummy.so
libgensio_perf.so
libgensiomdns.so.4.0.0
libgensio_python_swig.so.4
libgensio_kiss.so
libgensio_msgdelim.so
gensio_binary.libs/libgensio-ec088297.so.4.0.0
gensio_binary.libs/libgensiomdns-3883a74c.so.4.0.0
gensio_binary.libs/libgensio_python_swig-a1360fca.so.4.0.0
gensio_binary.libs/libgensioosh-91d44120.so.4.0.0
gensio_binary-2.6.2.post0.dist-info/METADATA
gensio_binary-2.6.2.post0.dist-info/WHEEL
gensio_binary-2.6.2.post0.dist-info/RECORD
gensio_binary-2.6.2.post0.dist-info/COPYING
gensio_binary-2.6.2.post0.dist-info/AUTHORS
gensio_binary-2.6.2.post0.dist-info/top_level.txt
gensio_binary-2.6.2.post0.dist-info/COPYING.LIB
