Metadata-Version: 2.1
Name: gensio-binary
Version: 2.6.2.post0
Summary: a framework for giving a consistent view of various stream (and packet) I/O types
Home-page: https://github.com/masenf/gensio
Author: Corey Minyard
Author-email: cminyard@mvista.com
Maintainer: Masen Furer
Maintainer-email: m_github@0x26.net
License: UNKNOWN
Platform: UNKNOWN
License-File: COPYING
License-File: COPYING.LIB
License-File: AUTHORS
